jupyterlab_liveupdate/__init__.py
jupyterlab_liveupdate/_version.py
jupyterlab_liveupdate/handlers.py
jupyterlab_liveupdate/tests/__init__.py
jupyterlab_liveupdate/tests/test_handlers.py
jupyterlab_liveupdate-0.1.1.data/data/etc/jupyter/jupyter_notebook_config.d/jupyterlab_liveupdate.json
jupyterlab_liveupdate-0.1.1.data/data/etc/jupyter/jupyter_server_config.d/jupyterlab_liveupdate.json
jupyterlab_liveupdate-0.1.1.data/data/share/jupyter/labextensions/jupyterlab-liveupdate/build_log.json
jupyterlab_liveupdate-0.1.1.data/data/share/jupyter/labextensions/jupyterlab-liveupdate/package.json
jupyterlab_liveupdate-0.1.1.data/data/share/jupyter/labextensions/jupyterlab-liveupdate/schemas/jupyterlab-liveupdate/liveupdater.json
jupyterlab_liveupdate-0.1.1.data/data/share/jupyter/labextensions/jupyterlab-liveupdate/schemas/jupyterlab-liveupdate/package.json.orig
jupyterlab_liveupdate-0.1.1.data/data/share/jupyter/labextensions/jupyterlab-liveupdate/static/lib_index_js.491961157af4b71eeed0.js
jupyterlab_liveupdate-0.1.1.data/data/share/jupyter/labextensions/jupyterlab-liveupdate/static/lib_index_js.491961157af4b71eeed0.js.map
jupyterlab_liveupdate-0.1.1.data/data/share/jupyter/labextensions/jupyterlab-liveupdate/static/remoteEntry.feb31bcbf681326be886.js
jupyterlab_liveupdate-0.1.1.data/data/share/jupyter/labextensions/jupyterlab-liveupdate/static/remoteEntry.feb31bcbf681326be886.js.map
jupyterlab_liveupdate-0.1.1.data/data/share/jupyter/labextensions/jupyterlab-liveupdate/static/style.js
jupyterlab_liveupdate-0.1.1.data/data/share/jupyter/labextensions/jupyterlab-liveupdate/static/style_index_js.09b3b186c80f8ffb5c4e.js
jupyterlab_liveupdate-0.1.1.data/data/share/jupyter/labextensions/jupyterlab-liveupdate/static/style_index_js.09b3b186c80f8ffb5c4e.js.map
jupyterlab_liveupdate-0.1.1.data/data/share/jupyter/labextensions/jupyterlab-liveupdate/static/vendors-node_modules_css-loader_dist_runtime_api_js-node_modules_css-loader_dist_runtime_cssW-72eba1.f9ed9f8b6a1e428884ae.js
jupyterlab_liveupdate-0.1.1.dist-info/METADATA
jupyterlab_liveupdate-0.1.1.dist-info/WHEEL
jupyterlab_liveupdate-0.1.1.dist-info/licenses/LICENSE
jupyterlab_liveupdate-0.1.1.dist-info/RECORD
