Metadata-Version: 2.1
Name: jupyterlab_liveupdate
Version: 0.1.1
Summary: Trying to implement live update in jupyterlab
Project-URL: Homepage, https://gitlab.au.dk/au748067/jupyterlab-liveupdate
Project-URL: Bug Tracker, https://gitlab.au.dk/au748067/jupyterlab-liveupdate/issues
Project-URL: Repository, https://gitlab.au.dk/au748067/jupyterlab-liveupdate.git
Author-email: Julien M <julien.marzal@telecom-paris.fr>
License: BSD 3-Clause License
License-File: LICENSE
Classifier: Framework :: Jupyter
Classifier: Framework :: Jupyter :: JupyterLab
Classifier: Framework :: Jupyter :: JupyterLab :: 3
Classifier: Framework :: Jupyter :: JupyterLab :: Extensions
Classifier: Framework :: Jupyter :: JupyterLab :: Extensions :: Prebuilt
Classifier: License :: OSI Approved :: BSD License
Classifier: Programming Language :: Python
Classifier: Programming Language :: Python :: 3
Classifier: Programming Language :: Python :: 3.7
Classifier: Programming Language :: Python :: 3.8
Classifier: Programming Language :: Python :: 3.9
Classifier: Programming Language :: Python :: 3.10
Classifier: Programming Language :: Python :: 3.11
Requires-Python: >=3.7
Requires-Dist: jupyter-server<3,>=1.21
Provides-Extra: test
Requires-Dist: coverage; extra == 'test'
Requires-Dist: pytest; extra == 'test'
Requires-Dist: pytest-asyncio; extra == 'test'
Requires-Dist: pytest-cov; extra == 'test'
Requires-Dist: pytest-jupyter[server]>=0.6.0; extra == 'test'
